smm/__init__.py
smm/analyzer.py
smm/dataloader.py
smm/main.py
smm/utils/__init__.py
smm/utils/io_utils.py
smm/utils/math_utils.py
smm/utils/plotting.py
smm/utils/unit_utils.py
smm_toolkit-0.1.4.2.dist-info/licenses/LICENSE
smm_toolkit-0.1.4.2.dist-info/METADATA
smm_toolkit-0.1.4.2.dist-info/WHEEL
smm_toolkit-0.1.4.2.dist-info/top_level.txt
smm_toolkit-0.1.4.2.dist-info/RECORD
