Metadata-Version: 2.4
Name: smm-toolkit
Version: 0.1.4.2
Summary: A Python toolkit for computing Soil Moisture Memory (SMM) based on drydown analysis and exponential decay fitting, as described in Farmani et al. (2025), Hydrology and Earth System Sciences.
Author-email: Mohammad Ali Farmani <mohammadalifarmani95@gmail.com>
Project-URL: Homepage, https://github.com/mfarmani95/SMM-Project
Project-URL: Documentation, https://pypi.org/project/smm-toolkit/
Project-URL: Source, https://github.com/mfarmani95/SMM-Project
Project-URL: Issue Tracker, https://github.com/mfarmani95/SMM-Project/issues
Project-URL: Related Paper, https://doi.org/10.5194/hess-29-547-2025
Keywords: hydrology,soil moisture,SMM,drydown analysis,land surface modeling,hydrologic modeling,Noah-MP,hydroclimate,timescales
Classifier: Development Status :: 4 - Beta
Classifier: Intended Audience :: Science/Research
Classifier: Topic :: Scientific/Engineering :: Hydrology
Classifier: License :: OSI Approved :: MIT License
Classifier: Programming Language :: Python :: 3
Classifier: Programming Language :: Python :: 3.9
Classifier: Programming Language :: Python :: 3.10
Classifier: Operating System :: OS Independent
Requires-Python: >=3.9
License-File: LICENSE
Requires-Dist: numpy>=1.21
Requires-Dist: pandas>=1.3
Requires-Dist: xarray>=2023.1.0
Requires-Dist: netCDF4
Requires-Dist: scipy>=1.8
Requires-Dist: matplotlib>=3.5
Requires-Dist: PyYAML>=6.0
Dynamic: license-file
